{
  "data": [
    {
      "id": 1,
      "contents": [
        {
          "imageSrc": "/assets/img/dress1_wegotmarried.png",
          "action": {
            "type": "normal",
            "text": "2023년 8월 19일 토요일 오후 1시",
            "color": "#ff9db7"
          }
        },
        {
          "imageSrc": "/assets/img/dress1_bigsmile.png",
          "action": {
            "type": "link",
            "text": "라마다 신도림 위치 안내",
            "color": "#76bcfb",
            "href": "https://map.naver.com/v5/entry/place/1080713347?c=15,0,0,0,dh",
            "mobileLink": "https://map.naver.com/v5/entry/place/1080713347?c=15,0,0,0,dh",
            "pcLink": "https://map.naver.com/v5/entry/place/1080713347?c=15,0,0,0,dh"
          }
        },
        {
          "imageSrc": "/assets/img/deco1.png",
          "action": {
            "type": "bottom-sheet_account",
            "text": "축의 계좌 정보",
            "color": "#61be7a"
          }
        }
      ],
      "description": "저희 결혼해요!\n2023년 8월 19일 토요일 오후 1시 정각\n라마다 서울 신도림 호텔 5F 세인트그레이스홀",
      "createdAt": "2023-02-27"
    },
    {
      "id": 2,
      "contents": [
        {
          "imageSrc": "/assets/img/dress2_flowerhand_face.jpg"
        },
        {
          "imageSrc": "/assets/img/temp.jpg"
        },
        {
          "imageSrc": "/assets/img/temp.jpg"
        }
      ],
      "description": "피드 설명",
      "tags": ["태그1", "태그2"]
    }
  ]
}